fglatch/__init__.py
fglatch/_main.py
fglatch/py.typed
fglatch/_client/__init__.py
fglatch/_client/enums.py
fglatch/_client/latch_client.py
fglatch/_client/models.py
fglatch/_tools/__init__.py
fglatch/_tools/submit.py
fglatch/registry/__init__.py
fglatch/registry/_record_model.py
fglatch/registry/_registry.py
fglatch/type_aliases/__init__.py
fglatch/type_aliases/_type_aliases.py
fglatch/workflows/__init__.py
fglatch/workflows/_provenance.py
fglatch-0.4.0.dist-info/METADATA
fglatch-0.4.0.dist-info/WHEEL
fglatch-0.4.0.dist-info/entry_points.txt
fglatch-0.4.0.dist-info/licenses/LICENSE
fglatch-0.4.0.dist-info/RECORD
