Metadata-Version: 2.4
Name: fglatch
Version: 0.4.0
Summary: CLI and Python extensions for the LatchBio platform.
Project-URL: homepage, https://github.com/fulcrumgenomics/fglatch
Project-URL: repository, https://github.com/fulcrumgenomics/fglatch
Project-URL: Bug Tracker, https://github.com/fulcrumgenomics/fglatch/issues
Author-email: Fulcrum Genomics LLC <contact@fulcrumgenomics.com>
License-Expression: MIT
License-File: LICENSE
Classifier: Development Status :: 3 - Alpha
Classifier: Intended Audience :: Developers
Classifier: Intended Audience :: Science/Research
Classifier: License :: OSI Approved :: MIT License
Classifier: Natural Language :: English
Classifier: Operating System :: OS Independent
Classifier: Programming Language :: Python :: 3
Classifier: Programming Language :: Python :: 3.12
Classifier: Programming Language :: Python :: 3.13
Classifier: Typing :: Typed
Requires-Python: >=3.12
Requires-Dist: defopt~=6.4
Requires-Dist: latch<3,>=2.67.2
Requires-Dist: pydantic~=2.11
Requires-Dist: pytest-asyncio>=1.2.0
Requires-Dist: requests-ratelimiter~=0.7
Requires-Dist: requests~=2.31
Requires-Dist: xattr~=1.1
